sphinx_k3d_screenshot/__init__.py
sphinx_k3d_screenshot/_version.py
sphinx_k3d_screenshot/plot_directive.py
sphinx_k3d_screenshot/utils.py
sphinx_k3d_screenshot-0.2.1.dist-info/licenses/LICENSE
sphinx_k3d_screenshot-0.2.1.dist-info/METADATA
sphinx_k3d_screenshot-0.2.1.dist-info/WHEEL
sphinx_k3d_screenshot-0.2.1.dist-info/top_level.txt
sphinx_k3d_screenshot-0.2.1.dist-info/RECORD
