Metadata-Version: 2.4
Name: sphinx_k3d_screenshot
Version: 0.2.1
Summary: A directive to include K3D Jupyter's screenshots into a Sphinx document
Home-page: https://github.com/Davide-sd/sphinx_k3d_screenshot
Author: Davide Sandona
Author-email: sandona.davide@gmail.com
License: MIT License
Keywords: k3d jupyter sphinx screenshot
Classifier: Development Status :: 4 - Beta
Classifier: License :: OSI Approved :: MIT License
Classifier: Programming Language :: Python :: 3.10
Classifier: Topic :: Documentation
Classifier: Topic :: Documentation :: Sphinx
License-File: LICENSE
Requires-Dist: k3d
Requires-Dist: selenium
Requires-Dist: webdriver_manager
Requires-Dist: sphinx
Requires-Dist: pillow
Requires-Dist: flask
Requires-Dist: ipykernel
Provides-Extra: dev
Requires-Dist: pytest; extra == "dev"
Dynamic: author
Dynamic: author-email
Dynamic: classifier
Dynamic: description
Dynamic: description-content-type
Dynamic: home-page
Dynamic: keywords
Dynamic: license
Dynamic: license-file
Dynamic: provides-extra
Dynamic: requires-dist
Dynamic: summary
